README.txt
setup.py
src/gaebuild/__init__.py
src/gaebuild/dist_installer.py
src/gaebuild/gaebuild.py
src/gaebuild/installer.py
src/gaebuild/templates.py
src/gaebuild.egg-info/PKG-INFO
src/gaebuild.egg-info/SOURCES.txt
src/gaebuild.egg-info/dependency_links.txt
src/gaebuild.egg-info/entry_points.txt
src/gaebuild.egg-info/not-zip-safe
src/gaebuild.egg-info/requires.txt
src/gaebuild.egg-info/top_level.txt