Metadata-Version: 1.0
Name: gaebuild
Version: 0.2.4
Summary: Buildout recipe for Google app engine
Home-page: https://github.com/carlitux/gaebuild
Author: Luis C. Cruz
Author-email: carlitos.kyo@gmail.com
License: BSD
Platform: UNKNOWN
Classifier: Framework :: Buildout
Classifier: Topic :: Software Development :: Build Tools
Classifier: Development Status :: 4 - Beta
Classifier: License :: OSI Approved :: BSD License
